<?xml version="1.0" encoding="UTF-8"?>
<list xmlns:xsi="http://www.w3.org/2001/XMLSchema-instance" xsi:noNamespaceSchemaLocation="../xsd/multisell.xsd">
	<npcs>
		<npc>30688</npc> <!-- Fishing Guildsman -->
	</npcs>
	<item>
		<ingredient id="91663" count="10000" />
		<ingredient id="97145" count="50000" />
		<production id="105811" count="1"/>
	</item>
	<item>
		<ingredient id="91663" count="10000" />
		<ingredient id="97145" count="50000" />
		<production id="105812" count="1"/>
	</item>
	<item>
		<ingredient id="91663" count="10000" />
		<ingredient id="97145" count="50000" />
		<production id="105813" count="1"/>
	</item>
	<item>
		<ingredient id="91663" count="10000" />
		<ingredient id="97145" count="50000" />
		<production id="105814" count="1"/>
	</item>
	<item>
		<ingredient id="91663" count="10000" />
		<ingredient id="97145" count="50000" />
		<production id="105815" count="1"/>
	</item>
	<item>
		<ingredient id="91663" count="10000" />
		<ingredient id="97145" count="50000" />
		<production id="105816" count="1"/>
	</item>
	<item>
		<ingredient id="91663" count="10000" />
		<ingredient id="97145" count="50000" />
		<production id="105817" count="1"/>
	</item>
	<item>
		<ingredient id="91663" count="10000" />
		<ingredient id="97145" count="50000" />
		<production id="105818" count="1"/>
	</item>
	<item>
		<ingredient id="91663" count="10000" />
		<ingredient id="97145" count="50000" />
		<production id="105819" count="1"/>
	</item>
	<item>
		<ingredient id="91663" count="10000" />
		<ingredient id="97145" count="50000" />
		<production id="105820" count="1"/>
	</item>
	<item>
		<ingredient id="91663" count="10000" />
		<ingredient id="97145" count="50000" />
		<production id="105821" count="1"/>
	</item>
	<item>
		<ingredient id="91663" count="10000" />
		<ingredient id="97145" count="50000" />
		<production id="105822" count="1"/>
	</item>

</list>